pyenv_manager_cli/__init__.py
pyenv_manager_cli/cli.py
pyenv_manager_cli/tests/__init__.py
pyenv_manager_cli-0.3.1.dist-info/METADATA
pyenv_manager_cli-0.3.1.dist-info/WHEEL
pyenv_manager_cli-0.3.1.dist-info/entry_points.txt
pyenv_manager_cli-0.3.1.dist-info/licenses/LICENSE
pyenv_manager_cli-0.3.1.dist-info/RECORD
