Metadata-Version: 2.4
Name: pyenv-manager-cli
Version: 0.3.1
Summary: A CLI tool for managing Python virtual environments with pyenv
Project-URL: Homepage, https://github.com/terrylica/pyenv-manager-cli
Project-URL: Repository, https://github.com/terrylica/pyenv-manager-cli.git
Author-email: Terry Li <terrylica@gmail.com>
License: MIT License
License-File: LICENSE
Keywords: environment,management,pyenv,python,virtualenv
Classifier: Development Status :: 4 - Beta
Classifier: Environment :: Console
Classifier: Intended Audience :: Developers
Classifier: License :: OSI Approved :: MIT License
Classifier: Programming Language :: Python :: 3
Classifier: Programming Language :: Python :: 3.8
Classifier: Programming Language :: Python :: 3.9
Classifier: Programming Language :: Python :: 3.10
Classifier: Programming Language :: Python :: 3.11
Classifier: Programming Language :: Python :: 3.12
Classifier: Programming Language :: Python :: 3.13
Requires-Python: >=3.8
Requires-Dist: click>=8.0.0
Provides-Extra: test
Requires-Dist: pytest-cov>=4.0.0; extra == 'test'
Requires-Dist: pytest>=7.0.0; extra == 'test'
